imarapy-0.1.7.dist-info/METADATA
imarapy-0.1.7.dist-info/WHEEL
imarapy/__init__.py
imarapy/imarapy.cpython-310-darwin.so
imarapy-0.1.7.dist-info/RECORD
