Metadata-Version: 2.4
Name: imarapy
Version: 0.1.7
